{
  "1076": "ender_dragon",
  "1066": "camel",
  "1132": "zoglin",
  "1113": "sniffer",
  "1060": "bat",
  "1057": "armadillo",
  "1080": "fox",
  "1094": "ocelot",
  "1093": "mule",
  "1125": "vindicator",
  "1117": "stray",
  "1134": "zombie",
  "1110": "skeleton",
  "1089": "iron_golem",
  "1115": "spider",
  "1111": "skeleton_horse",
  "1059": "axolotl",
  "1063": "bogged",
  "1120": "trader_llama",
  "1082": "ghast",
  "1100": "piglin_brute",
  "1114": "snow_golem",
  "1123": "vex",
  "1069": "cod",
  "1077": "enderman",
  "1101": "pillager",
  "1107": "sheep",
  "1062": "blaze",
  "1112": "slime",
  "1124": "villager",
  "1136": "zombie_villager",
  "1072": "dolphin",
  "1095": "panda",
  "1105": "ravager",
  "1122": "turtle",
  "1099": "piglin",
  "1118": "strider",
  "1096": "parrot",
  "1067": "cave_spider",
  "1137": "zombified_piglin",
  "1086": "hoglin",
  "1127": "warden",
  "1084": "goat",
  "1108": "shulker",
  "1106": "salmon",
  "1128": "witch",
  "1135": "zombie_horse",
  "1068": "chicken",
  "1116": "squid",
  "1131": "wolf",
  "1121": "tropical_fish",
  "1065": "cat",
  "1092": "mooshroom",
  "1064": "breeze",
  "1070": "cow",
  "1091": "magma_cube",
  "1061": "bee",
  "1088": "husk",
  "1102": "polar_bear",
  "1129": "wither",
  "1078": "endermite",
  "1075": "elder_guardian",
  "1085": "guardian",
  "1119": "tadpole",
  "1090": "llama",
  "1130": "wither_skeleton",
  "1087": "horse",
  "1126": "wandering_trader",
  "1079": "evoker",
  "1097": "phantom",
  "1103": "pufferfish",
  "1104": "rabbit",
  "1073": "donkey",
  "1133": "creaking",
  "1071": "creeper",
  "1109": "silverfish",
  "1081": "frog",
  "1098": "pig",
  "1074": "drowned",
  "1058": "allay",
  "1083": "glow_squid"
}